stage_left/__init__.py
stage_left/date_parsers.py
stage_left/date_patterns.py
stage_left/formatters.py
stage_left/parser.py
stage_left/tag_patterns.py
stage_left/types.py
stage_left-0.3.0.dist-info/METADATA
stage_left-0.3.0.dist-info/WHEEL
stage_left-0.3.0.dist-info/licenses/LICENSE
stage_left-0.3.0.dist-info/RECORD
