Metadata-Version: 2.4
Name: stage-left
Version: 0.3.0
Summary: Parse [x]it! documents into python data structures
License-Expression: MIT
License-File: LICENSE
Author: chris48s
Requires-Python: >=3.10
Classifier: Programming Language :: Python :: 3
Classifier: Programming Language :: Python :: 3.10
Classifier: Programming Language :: Python :: 3.11
Classifier: Programming Language :: Python :: 3.12
Classifier: Programming Language :: Python :: 3.13
Classifier: Programming Language :: Python :: 3.14
Project-URL: Documentation, https://chris48s.github.io/stage-left
Project-URL: Home, https://github.com/chris48s/stage-left
Project-URL: Source, https://github.com/chris48s/stage-left
